FabricZhongwenWendang/README.md
FabricZhongwenWendang/__init__.py
FabricZhongwenWendang/__main__.py
FabricZhongwenWendang/file.epub
FabricZhongwenWendang/index.html
FabricZhongwenWendang/css/__init__.py
FabricZhongwenWendang/css/annotations.css
FabricZhongwenWendang/css/main.css
FabricZhongwenWendang/css/normalize.css
FabricZhongwenWendang/css/popup.css
FabricZhongwenWendang/font/__init__.py
FabricZhongwenWendang/font/fontello.eot
FabricZhongwenWendang/font/fontello.svg
FabricZhongwenWendang/font/fontello.ttf
FabricZhongwenWendang/font/fontello.woff
FabricZhongwenWendang/img/__init__.py
FabricZhongwenWendang/img/annotator-glyph-sprite.png
FabricZhongwenWendang/img/annotator-icon-sprite.png
FabricZhongwenWendang/img/apple-touch-icon.png
FabricZhongwenWendang/img/cancelfullscreen.png
FabricZhongwenWendang/img/close.png
FabricZhongwenWendang/img/fullscreen.png
FabricZhongwenWendang/img/loader.gif
FabricZhongwenWendang/img/menu-icon.png
FabricZhongwenWendang/img/save.png
FabricZhongwenWendang/img/saved.png
FabricZhongwenWendang/img/settings-s.png
FabricZhongwenWendang/img/settings.png
FabricZhongwenWendang/img/star.png
FabricZhongwenWendang/js/__init__.py
FabricZhongwenWendang/js/epub.js
FabricZhongwenWendang/js/epub.min.js
FabricZhongwenWendang/js/epub.min.map
FabricZhongwenWendang/js/hooks.min.js
FabricZhongwenWendang/js/hooks.min.map
FabricZhongwenWendang/js/reader.js
FabricZhongwenWendang/js/reader.js.map
FabricZhongwenWendang/js/reader.min.js
FabricZhongwenWendang/js/reader.min.map
FabricZhongwenWendang/js/hooks/__init__.py
FabricZhongwenWendang/js/hooks/extensions/__init__.py
FabricZhongwenWendang/js/hooks/extensions/highlight.js
FabricZhongwenWendang/js/libs/__init__.py
FabricZhongwenWendang/js/libs/jquery.min.js
FabricZhongwenWendang/js/libs/localforage.min.js
FabricZhongwenWendang/js/libs/screenfull.js
FabricZhongwenWendang/js/libs/screenfull.min.js
FabricZhongwenWendang/js/libs/zip.min.js
FabricZhongwenWendang/js/plugins/__init__.py
fabric_zhongwen_wendang-2024.3.1.0.dist-info/METADATA
fabric_zhongwen_wendang-2024.3.1.0.dist-info/WHEEL
fabric_zhongwen_wendang-2024.3.1.0.dist-info/entry_points.txt
fabric_zhongwen_wendang-2024.3.1.0.dist-info/top_level.txt
fabric_zhongwen_wendang-2024.3.1.0.dist-info/RECORD
